{
  "nist_800_53_r5": "",
  "controls": "",
  "- control_id": "cm-2",
  "control_name": "Baseline Configuration",
  "mapping_type": "primary",
  "relevance_score": "1.0",
  "implementation_coverage": "1.0",
  "evidence_provided": "[\"documentation\", \"process\"]",
  "last_analyzed": "2025-01-15T12:00:00Z",
  "semantic_keywords": "[\"compliance\", \"standards\", \"nist\", \"controls\", \"tagging\"]",
  "auto_generated": "false",
  "generated_date": "2025-01-15T12:00:00Z",
  "analysis_confidence": "1.0"
}